bitmask_decoder/__init__.py
bitmask_decoder/bitmask_decoder-Copy1.py
bitmask_decoder/bitmask_decoder.py
bitmask_decoder-0.0.7.dist-info/LICENSE
bitmask_decoder-0.0.7.dist-info/METADATA
bitmask_decoder-0.0.7.dist-info/WHEEL
bitmask_decoder-0.0.7.dist-info/top_level.txt
bitmask_decoder-0.0.7.dist-info/RECORD
