Metadata-Version: 2.1
Name: bitmask-decoder
Version: 0.0.7
Summary: Python package to decode day-of-week bitmasks
Home-page: https://github.com/RoelantDL/bitmask-decoder
Author: Stijn Maas
Author-email: stijn_maas@live.nl
License: UNKNOWN
Platform: UNKNOWN
Classifier: Programming Language :: Python :: 3
Classifier: License :: OSI Approved :: MIT License
Classifier: Operating System :: OS Independent
Requires-Python: >=3.6
